scrapy_redis/__init__.py
scrapy_redis/__init__.pyi
scrapy_redis/connection.py
scrapy_redis/connection.pyi
scrapy_redis/defaults.py
scrapy_redis/defaults.pyi
scrapy_redis/dupefilter.py
scrapy_redis/dupefilter.pyi
scrapy_redis/picklecompat.py
scrapy_redis/picklecompat.pyi
scrapy_redis/pipelines.py
scrapy_redis/pipelines.pyi
scrapy_redis/py.typed
scrapy_redis/queue.py
scrapy_redis/queue.pyi
scrapy_redis/scheduler.py
scrapy_redis/scheduler.pyi
scrapy_redis/spiders.py
scrapy_redis/spiders.pyi
scrapy_redis/stats.py
scrapy_redis/stats.pyi
scrapy_redis/utils.py
scrapy_redis/utils.pyi
scrapy_redis_statictyped-0.7.1.dist-info/AUTHORS.rst
scrapy_redis_statictyped-0.7.1.dist-info/LICENSE
scrapy_redis_statictyped-0.7.1.dist-info/METADATA
scrapy_redis_statictyped-0.7.1.dist-info/WHEEL
scrapy_redis_statictyped-0.7.1.dist-info/top_level.txt
scrapy_redis_statictyped-0.7.1.dist-info/RECORD
