Metadata-Version: 2.1
Name: scrapy-redis-statictyped
Version: 0.7.1
Summary: Redis-based components for Scrapy.
Home-page: https://github.com/synodriver/scrapy-redis-statictyped
Author: synodriver
Author-email: diguohuangjiajinweijun@gmail.com
License: MIT
Keywords: scrapy-redis
Platform: UNKNOWN
Classifier: Development Status :: 4 - Beta
Classifier: Intended Audience :: Developers
Classifier: License :: OSI Approved :: MIT License
Classifier: Natural Language :: English
Classifier: Programming Language :: Python :: 2
Classifier: Programming Language :: Python :: 2.7
Classifier: Programming Language :: Python :: 3
Classifier: Programming Language :: Python :: 3.4
Classifier: Programming Language :: Python :: 3.5
Requires-Dist: Scrapy (>=1.0)
Requires-Dist: redis (>=2.10)
Requires-Dist: six (>=1.5.2)
Requires-Dist: redis-py-cluster (>=2.1.2)
Requires-Dist: pyfilters
